klarda/__init__.py
klarda/apis.py
klarda/exceptions.py
klarda/providers.py
klarda/types.py
LICENSE
klarda_python_sdk-1.0.2.dist-info/LICENSE
klarda_python_sdk-1.0.2.dist-info/METADATA
klarda_python_sdk-1.0.2.dist-info/WHEEL
klarda_python_sdk-1.0.2.dist-info/RECORD
