Metadata-Version: 2.1
Name: klarda-python-sdk
Version: 1.0.2
Summary: Refined Python library for interaction with Klarda's APIs.
Home-page: https://klarda.com/
License: MIT
Keywords: klarda,sdk,blockchain,token
Author: Thinh Q.D. Pham
Author-email: thinh.pham@klarda.com> <pqducthinhbka@gmail.com
Requires-Python: >=3.8.1,<4.0.0
Classifier: License :: OSI Approved :: MIT License
Classifier: Programming Language :: Python :: 3
Classifier: Programming Language :: Python :: 3.9
Classifier: Programming Language :: Python :: 3.10
Classifier: Programming Language :: Python :: 3.11
Classifier: Programming Language :: Python :: 3.12
Requires-Dist: eth-typing (>=4.0.0,<5.0.0)
Requires-Dist: pydantic (>=2.0.8,<3.0.0)
Requires-Dist: pyhumps (>=3.8.0,<4.0.0)
Requires-Dist: typing-extensions (>=4.6.2,<5.0.0)
Requires-Dist: urllib3 (>=2.0.0,<3.0.0)
Requires-Dist: web3 (>=6.4.0,<7.0.0)
Project-URL: Repository, https://github.com/klardaofficial/klarda-python-sdk
